setup.py
ccex/OKEx.py
ccex/__init__.py
ccex/general.py
ccex.egg-info/PKG-INFO
ccex.egg-info/SOURCES.txt
ccex.egg-info/dependency_links.txt
ccex.egg-info/top_level.txt