Metadata-Version: 1.0
Name: ccex
Version: 0.0.2
Summary: api for crypto currency exchange
Home-page: https://pypi.org/manage/projects/
Author: hd.zhang
Author-email: haidongboy@163.com
License: UNKNOWN
Platform: UNKNOWN
